{
    "/{{ asset('admin/assets/') }}css/pages/chat.css": "/{{ asset('admin/assets/') }}css/pages/chat.css",
    "/{{ asset('admin/assets/') }}css/pages/email.css": "/{{ asset('admin/assets/') }}css/pages/email.css",
    "/{{ asset('admin/assets/') }}css/pages/error.css": "/{{ asset('admin/assets/') }}css/pages/error.css",
    "/{{ asset('admin/assets/') }}css/pages/auth.css": "/{{ asset('admin/assets/') }}css/pages/auth.css",
    "/{{ asset('admin/assets/') }}css/bootstrap.css": "/{{ asset('admin/assets/') }}css/bootstrap.css",
    "/{{ asset('admin/assets/') }}css/app.css": "/{{ asset('admin/assets/') }}css/app.css",
    "/{{ asset('admin/assets/') }}css/widgets/todo.css": "/{{ asset('admin/assets/') }}css/widgets/todo.css",
    "/{{ asset('admin/assets/') }}css/widgets/chat.css": "/{{ asset('admin/assets/') }}css/widgets/chat.css"
}
